{
  "report_name": "daily_marketplace_returns",
  "returns_count": 7,
  "seller_summary": {
    "TechStore": {
      "returns_count": 3,
      "approved_refund_amount": 26390.0,
      "fraud_flags": 1,
      "total_units": 7
    },
    "HomeHub": {
      "returns_count": 2,
      "approved_refund_amount": 0.0,
      "fraud_flags": 0,
      "total_units": 2
    },
    "UrbanWear": {
      "returns_count": 2,
      "approved_refund_amount": 17390.0,
      "fraud_flags": 1,
      "total_units": 7
    }
  },
  "warehouse_summary": {
    "WH-MSK": {
      "returns_count": 2,
      "approved_refund_amount": 7400.0
    },
    "WH-SPB": {
      "returns_count": 2,
      "approved_refund_amount": 0.0
    },
    "WH-EKB": {
      "returns_count": 2,
      "approved_refund_amount": 17390.0
    },
    "WH-KZN": {
      "returns_count": 1,
      "approved_refund_amount": 18990.0
    }
  },
  "escalations": [
    {
      "return_id": "R-303",
      "seller": "TechStore",
      "warehouse": "WH-MSK",
      "reason": "fraud_suspected",
      "refund_amount": 22100.5,
      "status": "manual_review"
    },
    {
      "return_id": "R-307",
      "seller": "TechStore",
      "warehouse": "WH-KZN",
      "reason": "wrong_item",
      "refund_amount": 18990.0,
      "status": "approved"
    },
    {
      "return_id": "R-302",
      "seller": "HomeHub",
      "warehouse": "WH-SPB",
      "reason": "wrong_item",
      "refund_amount": 15990.0,
      "status": "manual_review"
    },
    {
      "return_id": "R-306",
      "seller": "UrbanWear",
      "warehouse": "WH-EKB",
      "reason": "fraud_suspected",
      "refund_amount": 12400.0,
      "status": "approved"
    }
  ]
}